[
  {
    "ddbId": 21,
    "cobaltId": null,
    "parentId": 431,
    "splitTag": "h3",
    "slug": "dragon-hatchery#DragonHatchery",
    "tagIdFirst": "1CaveEntrance",
    "contentChunkIdStart": "fde62b5f-9a47-46e2-82cd-599a23896502",
    "tagIdLast": "",
    "contentChunkIdStop": "EOF",
    "sceneName": "Dragon Hatchery"
  },{
    "ddbId": 33,
    "cobaltId": null,
    "parentId": 433,
    "splitTag": "h3",
    "slug": "construction-ahead#CarnathRoadhouse",
    "tagIdFirst": "1Courtyard",
    "contentChunkIdStart": "fb2c29d3-af3f-42f5-9204-0340fd57777c",
    "tagIdLast": "",
    "contentChunkIdStop": "EOF",
    "sceneName": "Carnath Roadhouse"
  },{
    "ddbId": 41,
    "cobaltId": null,
    "parentId": 434,
    "splitTag": "h3",
    "slug": "castle-naerytar#OutsideCastleNaerytar",
    "tagIdFirst": "1Landing",
    "contentChunkIdStart": "d6b8b9c3-c760-4d0f-90da-0ecab8c4f0d9",
    "tagIdLast": "",
    "contentChunkIdStop": "EOF",
    "sceneName": "Outside Castle Naerytar"
  },{
    "ddbId": 43,
    "cobaltId": null,
    "parentId": 434,
    "splitTag": "h3",
    "slug": "castle-naerytar#GroundFloor",
    "tagIdFirst": "1ABarbican",
    "contentChunkIdStart": "1b761c89-ec20-4db8-94c3-1ae8e039ba5c",
    "tagIdLast": "",
    "contentChunkIdStop": "EOF",
    "sceneName": "Ground Floor"
  },{
    "ddbId": 44,
    "cobaltId": null,
    "parentId": 434,
    "splitTag": "h3",
    "slug": "castle-naerytar#SecondFloor",
    "tagIdFirst": "2AUpperBarbican",
    "contentChunkIdStart": "489d3883-ab65-4977-b751-5ddca4bd4808",
    "tagIdLast": "",
    "contentChunkIdStop": "EOF",
    "sceneName": "Second Floor"
  },{
    "ddbId": 45,
    "cobaltId": null,
    "parentId": 434,
    "splitTag": "h3",
    "slug": "castle-naerytar#ThirdFloor",
    "tagIdFirst": "3ESpectersSanctum",
    "contentChunkIdStart": "a91bb078-8be9-49f0-beeb-9b23fea3c4f4",
    "tagIdLast": "",
    "contentChunkIdStop": "EOF",
    "sceneName": "Third Floor"
  },{
    "ddbId": 46,
    "cobaltId": null,
    "parentId": 434,
    "splitTag": "h3",
    "slug": "castle-naerytar#BeneaththeCastle",
    "tagIdFirst": "1EntryCavern",
    "contentChunkIdStart": "755af8d0-ad7e-40ad-aeb4-a961abe450b4",
    "tagIdLast": "",
    "contentChunkIdStop": "EOF",
    "sceneName": "Dungeon"
  },{
    "ddbId": 50,
    "cobaltId": null,
    "parentId": 435,
    "splitTag": "h3",
    "slug": "hunting-lodge#OutsidetheLodge",
    "tagIdFirst": "1PortalStones",
    "contentChunkIdStart": "49979aee-1a36-41cf-ba35-ee287c0d4358",
    "tagIdLast": "",
    "contentChunkIdStop": "EOF",
    "sceneName": "Hunting Lodge"
  },{
    "ddbId": 51,
    "cobaltId": null,
    "parentId": 435,
    "splitTag": "h3",
    "slug": "hunting-lodge#LodgeGroundFloor",
    "tagIdFirst": "4CloakRoomandGuardPost",
    "contentChunkIdStart": "8be7687b-beae-4394-a19c-75f70af7cad7",
    "tagIdLast": "",
    "contentChunkIdStop": "EOF",
    "sceneName": "Hunting Lodge"
  },{
    "ddbId": 52,
    "cobaltId": null,
    "parentId": 435,
    "splitTag": "h3",
    "slug": "hunting-lodge#LodgeUpperFloor",
    "tagIdFirst": "16TalissHall",
    "contentChunkIdStart": "06953e57-9daf-4a12-b3b1-8255bb377fd5",
    "tagIdLast": "",
    "contentChunkIdStop": "EOF",
    "sceneName": "Hunting Lodge"
  },{
    "ddbId": 55,
    "cobaltId": null,
    "parentId": 436,
    "splitTag": "h3",
    "slug": "castle-in-the-clouds#Parnast",
    "tagIdFirst": "1VillageofParnast",
    "contentChunkIdStart": "730fcbcb-87b3-4fc1-8ab9-7d8505d9be03",
    "tagIdLast": "",
    "contentChunkIdStop": "EOF",
    "sceneName": "Parnast"
  },{
    "ddbId": 57,
    "cobaltId": null,
    "parentId": 436,
    "splitTag": "h3",
    "slug": "castle-in-the-clouds#AreasoftheCastle615",
    "tagIdFirst": "6MainGate",
    "contentChunkIdStart": "ee7cccf2-1186-4c49-b4fd-5262765c4ec7",
    "tagIdLast": "",
    "contentChunkIdStop": "EOF",
    "sceneName": "Skyreach Castle"
  },{
    "ddbId": 58,
    "cobaltId": null,
    "parentId": 436,
    "splitTag": "h3",
    "slug": "castle-in-the-clouds#AreasoftheCastle1625",
    "tagIdFirst": "16UpperCourtyard",
    "contentChunkIdStart": "3f4ffbd9-cc3c-4164-82c3-8411827f39c8",
    "tagIdLast": "",
    "contentChunkIdStop": "EOF",
    "sceneName": "Skyreach Castle"
  }
]
